ping_cloud_utils/k8s.py
ping_cloud_utils-0.7.dist-info/METADATA
ping_cloud_utils-0.7.dist-info/WHEEL
ping_cloud_utils-0.7.dist-info/top_level.txt
ping_cloud_utils-0.7.dist-info/RECORD
