Metadata-Version: 2.1
Name: ping-cloud-utils
Version: 0.7
Summary: Library for management of K8s & AWS functionality common between repositories in PingCloud
Home-page: UNKNOWN
Author: surajthapa@pingidentity.com
Author-email: surajthapa@pingidentity.com
License: 2021 Ping
Platform: UNKNOWN
Classifier: Programming Language :: Python :: 3
Requires-Python: >=3
Requires-Dist: kubernetes (==24.2.0)
Requires-Dist: boto3 (==1.17.18)
Requires-Dist: more-itertools
